pythor/__init__.py
pythor/asset.py
pythor/benchmark.py
pythor/compustat.py
pythor/feature.py
pythor/neural.py
pythor/numerai.py
pythor/numerai_signals.py
pythor/optimisation.py
pythor/util.py
thorml-0.1.1.2.dist-info/LICENSE
thorml-0.1.1.2.dist-info/METADATA
thorml-0.1.1.2.dist-info/WHEEL
thorml-0.1.1.2.dist-info/top_level.txt
thorml-0.1.1.2.dist-info/RECORD
