Metadata-Version: 2.1
Name: thorml
Version: 0.1.1.2
Summary: AutoML tools for Tabular Datasets
Home-page: https://github.com/ThomasWong2022/thor-public
Author: Thomas Wong
Author-email: mw4315@ic.ac.uk
License: UNKNOWN
Project-URL: Documentation, https://github.com/ThomasWong2022/thor-public
Project-URL: Bug Reports, https://github.com/ThomasWong2022/thor-public/issues
Project-URL: Source Code, https://github.com/ThomasWong2022/thor-public
Keywords: autoML
Platform: UNKNOWN
Classifier: Development Status :: 3 - Alpha
Classifier: Intended Audience :: Developers
Classifier: Topic :: Software Development :: Build Tools
Classifier: Programming Language :: Python :: 3
Classifier: Programming Language :: Python :: 3.7
Classifier: Programming Language :: Python :: 3.8
Classifier: Programming Language :: Python :: 3.9
Classifier: Programming Language :: Python :: 3 :: Only
Classifier: License :: OSI Approved :: MIT License
Classifier: Operating System :: OS Independent
Requires-Python: >=3.7
License-File: LICENSE
Provides-Extra: dev
Requires-Dist: check-manifest ; extra == 'dev'
